kolibri_opensearch_plugin/__init__.py
kolibri_opensearch_plugin/kolibri_plugin.py
kolibri_opensearch_plugin/root_urls.py
kolibri_opensearch_plugin/views.py
kolibri_opensearch_plugin-0.0.3.dist-info/AUTHORS.rst
kolibri_opensearch_plugin-0.0.3.dist-info/LICENSE
kolibri_opensearch_plugin-0.0.3.dist-info/METADATA
kolibri_opensearch_plugin-0.0.3.dist-info/WHEEL
kolibri_opensearch_plugin-0.0.3.dist-info/entry_points.txt
kolibri_opensearch_plugin-0.0.3.dist-info/top_level.txt
kolibri_opensearch_plugin-0.0.3.dist-info/RECORD
