Metadata-Version: 2.1
Name: kolibri-opensearch-plugin
Version: 0.0.3
Summary: Kolibri plugin to provide an OpenSearch compatible API
Home-page: https://github.com/learningequality/kolibri-opensearch-plugin
Author: Learning Equality
Author-email: info@learningequality.org
License: MIT
Keywords: kolibri
Classifier: Development Status :: 4 - Beta
Classifier: Framework :: Django
Classifier: Intended Audience :: Developers
Classifier: License :: OSI Approved :: MIT License
Classifier: Natural Language :: English
Classifier: Programming Language :: Python :: 3
Classifier: Programming Language :: Python :: 3.6
Classifier: Programming Language :: Python :: 3.7
Classifier: Programming Language :: Python :: 3.8
Classifier: Programming Language :: Python :: 3.9
Classifier: Programming Language :: Python :: 3.10
Classifier: Programming Language :: Python :: 3.11
Classifier: Programming Language :: Python :: Implementation :: PyPy
Classifier: Topic :: Education :: Computer Aided Instruction (CAI)
Classifier: Topic :: Internet :: WWW/HTTP :: Indexing/Search
Requires-Python: >=3
License-File: LICENSE
License-File: AUTHORS.rst
Requires-Dist: feedgenerator
Provides-Extra: dev
Requires-Dist: setuptools ; extra == 'dev'
Requires-Dist: wheel ; extra == 'dev'
Requires-Dist: twine ; extra == 'dev'
